{
    "paths": [
        {
            "name": "/items",
            "lambdaFunction": "bsheadfoot595c1c9c",
            "privacy": {
                "open": true
            },
            "policyResourceName": "/items"
        }
    ],
    "resourceName": "api9ece3808",
    "apiName": "api9ece3808",
    "functionArns": [
        {
            "lambdaFunction": "bsheadfoot595c1c9c"
        }
    ],
    "privacy": {
        "auth": 0,
        "unauth": 0,
        "authRoleName": "amplify-bsheadfoot-local-13612-authRole",
        "unAuthRoleName": "amplify-bsheadfoot-local-13612-unauthRole"
    },
    "dependsOn": [
        {
            "category": "function",
            "resourceName": "bsheadfoot595c1c9c",
            "attributes": [
                "Name",
                "Arn"
            ]
        }
    ]
}